lucasdp/__init__.py
lucasdp/db/__init__.py
lucasdp/db/db_connection.py
lucasdp/db/query_handler.py
lucasdp/db/sqlalchemy_utils.py
lucasdp/db/standardize_sql_column_names.py
lucasdp/logging/__init__.py
lucasdp/logging/prefect_log_config.py
lucasdp-0.6.12.dist-info/METADATA
lucasdp-0.6.12.dist-info/WHEEL
lucasdp-0.6.12.dist-info/top_level.txt
lucasdp-0.6.12.dist-info/RECORD
