Metadata-Version: 2.1
Name: lucasdp
Version: 0.6.12
Summary: Modulos comunes para proyectos de datos
Author: Lucas Depetris
Author-email: lucasdepetris14@gmail.com
Requires-Dist: keyring
Requires-Dist: pandas
Requires-Dist: prefect
Requires-Dist: sqlalchemy
